simstring_rust-0.3.3.dist-info/METADATA
simstring_rust-0.3.3.dist-info/WHEEL
simstring_rust-0.3.3.dist-info/licenses/LICENSE
simstring_rust/__init__.py
simstring_rust/simstring_rust.abi3.so
simstring_rust-0.3.3.dist-info/RECORD
