Metadata-Version: 2.4
Name: simstring-rust
Version: 0.3.3
Classifier: Programming Language :: Rust
Classifier: Programming Language :: Python :: Implementation :: CPython
Classifier: Programming Language :: Python :: 3
Classifier: Programming Language :: Python :: 3.10
Classifier: Programming Language :: Python :: 3.11
Classifier: Programming Language :: Python :: 3.12
Classifier: Programming Language :: Python :: 3.13
Classifier: License :: OSI Approved :: MIT License
Classifier: Operating System :: POSIX
Classifier: Operating System :: MacOS :: MacOS X
Classifier: Operating System :: Microsoft :: Windows
License-File: LICENSE
Summary: A fast, native Rust implementation of the SimString algorithm with Python bindings.
Keywords: string-matching,nlp,simstring,fuzzy
Home-Page: https://github.com/PyDataBlog/simstring_rs
Author-email: Bernard Brenyah <bbrenyah@gmail.com>
License: MIT
Requires-Python: >=3.10
Project-URL: Homepage, https://github.com/PyDataBlog/simstring_rs
Project-URL: Repository, https://github.com/PyDataBlog/simstring_rs
